{
  "points": {
    "p1": {
      "ORIGINAL": {
        "x": 0.6156184929834163,
        "y": 0.08539832151226268
      },
      "L1": {
        "x": 0.2205719658735506,
        "y": 0.4002980124191997,
        "l1_norm": 0.7099462180168028,
        "l2_norm": 0.25522357391485034,
        "non_zero_results": 2
      },
      "L2": {
        "x": 0.2232426159941696,
        "y": 0.4555388728494922,
        "l1_norm": 0.7625164283264763,
        "l2_norm": 0.2909628565873087,
        "non_zero_results": 2
      }
    },
    "p2": {
      "ORIGINAL": {
        "x": 1.0189514043843646,
        "y": 3.173
      },
      "L1": {
        "x": 0.9831491406582552,
        "y": 3.173,
        "l1_norm": 0.035802263726109396,
        "l2_norm": 0.0012818020879138887,
        "non_zero_results": 1
      },
      "L2": {
        "x": 0.9374231716960814,
        "y": 3.1853877112750775,
        "l1_norm": 0.09391594396336067,
        "l2_norm": 0.006800308115909536,
        "non_zero_results": 2
      }
    },
    "p3": {
      "ORIGINAL": {
        "x": 2.99,
        "y": 0.52793350909513
      },
      "L1": {
        "x": 2.99,
        "y": 0.5271290190447607,
        "l1_norm": 0.0008044900503693109,
        "l2_norm": 6.472042411432164e-07,
        "non_zero_results": 1
      },
      "L2": {
        "x": 2.972780475297461,
        "y": 0.615950479825096,
        "l1_norm": 0.10523649543250502,
        "l2_norm": 0.008043499167461035,
        "non_zero_results": 2
      }
    },
    "p4": {
      "ORIGINAL": {
        "x": 2.031995020634442,
        "y": -2.517
      },
      "L1": {
        "x": 1.3183985090772936,
        "y": -2.517,
        "l1_norm": 0.7135965115571483,
        "l2_norm": 0.5092199813065313,
        "non_zero_results": 1
      },
      "L2": {
        "x": 1.4965181511159718,
        "y": -2.8036997196035776,
        "l1_norm": 0.8221765891220478,
        "l2_norm": 0.3689322070100708,
        "non_zero_results": 2
      }
    },
    "p5": {
      "ORIGINAL": {
        "x": -1.8489975458714059,
        "y": -2.517
      },
      "L1": {
        "x": -2.3418905255038065,
        "y": -1.6469100560119694
      },
      "L2": {
        "x": -2.3418905255038065,
        "y": -1.6469100560119694
      }
    },
    "p6": {
      "ORIGINAL": {
        "x": -3.0,
        "y": 1.8055
      },
      "L1": {
        "x": -3.0,
        "y": 2.5220894567010648,
        "l1_norm": 0.7165894567010647,
        "l2_norm": 0.5135004494551271,
        "non_zero_results": 1
      },
      "L2": {
        "x": -2.738215658974132,
        "y": 2.3539213726232235,
        "l1_norm": 0.8102057136490914,
        "l2_norm": 0.3692970431562884,
        "non_zero_results": 2
      }
    }
  },
  "lines": {
    "l1": [
      "p1",
      "p2"
    ],
    "l2": [
      "p1",
      "p3"
    ],
    "l3": [
      "p1",
      "p4"
    ],
    "l4": [
      "p1",
      "p5"
    ],
    "l5": [
      "p1",
      "p6"
    ],
    "l6": [
      "p2",
      "p3"
    ],
    "l7": [
      "p3",
      "p4"
    ],
    "l8": [
      "p4",
      "p5"
    ],
    "l9": [
      "p5",
      "p6"
    ],
    "l10": [
      "p6",
      "p2"
    ]
  },
  "circles": {},
  "constraints": {
    "c1": {
      "type": "ANGLE",
      "entities": [
        "l1",
        "l2"
      ],
      "value": -1.2566370614359172
    },
    "c2": {
      "type": "ANGLE",
      "entities": [
        "l2",
        "l3"
      ],
      "value": -1.2566370614359172
    },
    "c3": {
      "type": "ANGLE",
      "entities": [
        "l3",
        "l4"
      ],
      "value": -1.2566370614359172
    },
    "c4": {
      "type": "ANGLE",
      "entities": [
        "l4",
        "l5"
      ],
      "value": -1.2566370614359172
    }
  },
  "moves": {
    "m1": {
      "point": "p5",
      "values": [
        -2.3418905255038065,
        -1.6469100560119694
      ]
    }
  },
  "Results": {
    "l1_norm": {
      "L1": 2.1767389400514947,
      "L2": 2.594051170493481
    },
    "l2_norm": {
      "L1": 1.279226453968664,
      "L2": 1.0440359140370385
    },
    "non_zero_results": {
      "L1": 6,
      "L2": 10
    },
    "variables": 12,
    "time": {
      "L1": 0.002566099166870117,
      "L2": 0.0014171600341796875
    },
    "steps": {
      "L1": 4,
      "L2": 4
    }
  }
}