{
  "points": {
    "p1": {
      "ORIGINAL": {
        "x": 0.6156184929834163,
        "y": 0.08539832151226268
      },
      "L1": {
        "x": 0.7890980972043318,
        "y": 0.30591120277123496,
        "l1_norm": 0.39399248547988774,
        "l2_norm": 0.07872110388177908,
        "non_zero_results": 2
      },
      "L2": {
        "x": 0.7736430647133764,
        "y": 0.33722027475013683,
        "l1_norm": 0.40984652496783425,
        "l2_norm": 0.08838606140297538,
        "non_zero_results": 2
      }
    },
    "p2": {
      "ORIGINAL": {
        "x": 1.0189514043843646,
        "y": 3.173
      },
      "L1": {
        "x": 1.41105972871883,
        "y": 3.173,
        "l1_norm": 0.3921083243344654,
        "l2_norm": 0.15374893801238232,
        "non_zero_results": 1
      },
      "L2": {
        "x": 1.361099511890122,
        "y": 3.1259452795937084,
        "l1_norm": 0.38920282791204897,
        "l2_norm": 0.11927947418228554,
        "non_zero_results": 2
      }
    },
    "p3": {
      "ORIGINAL": {
        "x": 2.99,
        "y": 0.52793350909513
      },
      "L1": {
        "x": 2.99,
        "y": 0.5279335085121163,
        "l1_norm": 5.830137483897602e-10,
        "l2_norm": 3.3990503081147858e-19,
        "non_zero_results": 1
      },
      "L2": {
        "x": 2.9824122135931472,
        "y": 0.5734384157716763,
        "l1_norm": 0.053092693083399256,
        "l2_norm": 0.0021282710341972086,
        "non_zero_results": 2
      }
    },
    "p4": {
      "ORIGINAL": {
        "x": 2.031995020634442,
        "y": -2.517
      },
      "L1": {
        "x": 2.03181977685289,
        "y": -2.517,
        "l1_norm": 0.00017524378155187037,
        "l2_norm": 3.0710382972599663e-08,
        "non_zero_results": 1
      },
      "L2": {
        "x": 2.047081832637623,
        "y": -2.5090107089201976,
        "l1_norm": 0.023076103082983135,
        "l2_norm": 0.00029144066837713013,
        "non_zero_results": 2
      }
    },
    "p5": {
      "ORIGINAL": {
        "x": -1.8489975458714059,
        "y": -2.517
      },
      "L1": {
        "x": -2.275575733816854,
        "y": -2.4304133297095603,
        "l1_norm": 0.5131648582358876,
        "l2_norm": 0.18946620190280725,
        "non_zero_results": 2
      },
      "L2": {
        "x": -2.1085396197167796,
        "y": -2.2674272584868556,
        "l1_norm": 0.5091148153585181,
        "l2_norm": 0.1296486414023442,
        "non_zero_results": 2
      }
    },
    "p6": {
      "ORIGINAL": {
        "x": -3.0,
        "y": 1.8055
      },
      "L1": {
        "x": -2.0086622237606564,
        "y": 1.9368370222017903
      },
      "L2": {
        "x": -2.0086622237606564,
        "y": 1.9368370222017903
      }
    }
  },
  "lines": {
    "l1": [
      "p1",
      "p2"
    ],
    "l2": [
      "p1",
      "p3"
    ],
    "l3": [
      "p1",
      "p4"
    ],
    "l4": [
      "p1",
      "p5"
    ],
    "l5": [
      "p1",
      "p6"
    ],
    "l6": [
      "p2",
      "p3"
    ],
    "l7": [
      "p3",
      "p4"
    ],
    "l8": [
      "p4",
      "p5"
    ],
    "l9": [
      "p5",
      "p6"
    ],
    "l10": [
      "p6",
      "p2"
    ]
  },
  "circles": {},
  "constraints": {
    "c1": {
      "type": "ANGLE",
      "entities": [
        "l1",
        "l2"
      ],
      "value": -1.2566370614359172
    },
    "c2": {
      "type": "ANGLE",
      "entities": [
        "l2",
        "l3"
      ],
      "value": -1.2566370614359172
    },
    "c3": {
      "type": "ANGLE",
      "entities": [
        "l3",
        "l4"
      ],
      "value": -1.2566370614359172
    },
    "c4": {
      "type": "ANGLE",
      "entities": [
        "l4",
        "l5"
      ],
      "value": -1.2566370614359172
    }
  },
  "moves": {
    "m1": {
      "point": "p6",
      "values": [
        -2.0086622237606564,
        1.9368370222017903
      ]
    }
  },
  "Results": {
    "l1_norm": {
      "L1": 1.2994409124148065,
      "L2": 1.3843329644047837
    },
    "l2_norm": {
      "L1": 0.4219362745073516,
      "L2": 0.33973388869017945
    },
    "non_zero_results": {
      "L1": 7,
      "L2": 10
    },
    "variables": 12,
    "time": {
      "L1": 0.002484560012817383,
      "L2": 0.0013036727905273438
    },
    "steps": {
      "L1": 4,
      "L2": 4
    }
  }
}