{
  "points": {
    "p1": {
      "ORIGINAL": {
        "x": 0.0,
        "y": 1.0
      },
      "L1": {
        "x": -2.7064452598091693,
        "y": 1.0318224864048129,
        "l1_norm": 2.738267746213982,
        "l2_norm": 7.325858614984506,
        "non_zero_results": 2
      },
      "L2": {
        "x": -1.5613014407612658,
        "y": -0.80660639959416,
        "l1_norm": 3.367907840355426,
        "l2_norm": 5.701488871977777,
        "non_zero_results": 2
      }
    },
    "p2": {
      "ORIGINAL": {
        "x": 4.0,
        "y": 1.0
      },
      "L1": {
        "x": 0.9880418453943043,
        "y": 2.5650429628808036,
        "l1_norm": 4.5770011174865,
        "l2_norm": 11.521251400758473,
        "non_zero_results": 2
      },
      "L2": {
        "x": 1.4186665220514054,
        "y": 1.8616872387841432,
        "l1_norm": 3.443020716732738,
        "l2_norm": 7.405787421861627,
        "non_zero_results": 2
      }
    },
    "p3": {
      "ORIGINAL": {
        "x": 4.0,
        "y": 3.0
      },
      "L1": {
        "x": 1.1347873511752034,
        "y": 2.211441255121076
      },
      "L2": {
        "x": 1.1054927872116662,
        "y": 2.2114417347638025
      }
    }
  },
  "lines": {
    "l1": [
      "p1",
      "p2"
    ],
    "l2": [
      "p2",
      "p3"
    ],
    "l3": [
      "p3",
      "p1"
    ]
  },
  "circles": {},
  "constraints": {
    "c1": {
      "type": "LENGTH",
      "entities": [
        "l1"
      ],
      "value": 4
    },
    "c4": {
      "type": "ORTHOGONAL",
      "entities": [
        "l1",
        "l2"
      ]
    }
  },
  "moves": {
    "m1": {
      "point": "p3",
      "values": [
        1.1054922515434553,
        2.211441255121076
      ]
    }
  },
  "Results": {
    "l1_norm": {
      "L1": 7.3152688637004815,
      "L2": 6.810928557088164
    },
    "l2_norm": {
      "L1": 18.847110015742977,
      "L2": 13.107276293839405
    },
    "non_zero_results": {
      "L1": 4,
      "L2": 4
    },
    "variables": 6,
    "time": {
      "L1": 0.0011489391326904297,
      "L2": 0.000240325927734375
    },
    "steps": {
      "L1": 7,
      "L2": 5
    }
  }
}