{
  "points": {
    "p1": {
      "ORIGINAL": {
        "x": 0.0,
        "y": 1.0
      },
      "L1": {
        "x": -0.5326580121577138,
        "y": 1.0,
        "l1_norm": 0.5326580121577138,
        "l2_norm": 0.2837245579158072,
        "non_zero_results": 1
      },
      "L2": {
        "x": -0.35032631450801827,
        "y": 0.9297883605884928,
        "l1_norm": 0.4205379539195255,
        "l2_norm": 0.12765820094562244,
        "non_zero_results": 2
      }
    },
    "p2": {
      "ORIGINAL": {
        "x": 4.0,
        "y": 1.0
      },
      "L1": {
        "x": 3.4167652113402966,
        "y": 1.6340790184942162,
        "l1_norm": 1.2173138071539196,
        "l2_norm": 0.7422190203975174,
        "non_zero_results": 2
      },
      "L2": {
        "x": 3.6481587216864195,
        "y": 1.039867492903247,
        "l1_norm": 0.39170877121682746,
        "l2_norm": 0.12538170211572486,
        "non_zero_results": 2
      }
    },
    "p3": {
      "ORIGINAL": {
        "x": 4.0,
        "y": 3.0
      },
      "L1": {
        "x": 3.6763043208869792,
        "y": 0.01751427379747339
      },
      "L2": {
        "x": 3.6763043203899888,
        "y": 0.01751427379747339
      }
    }
  },
  "lines": {
    "l1": [
      "p1",
      "p2"
    ],
    "l2": [
      "p2",
      "p3"
    ],
    "l3": [
      "p3",
      "p1"
    ]
  },
  "circles": {},
  "constraints": {
    "c1": {
      "type": "LENGTH",
      "entities": [
        "l1"
      ],
      "value": 4
    },
    "c4": {
      "type": "ORTHOGONAL",
      "entities": [
        "l1",
        "l2"
      ]
    }
  },
  "moves": {
    "m1": {
      "point": "p3",
      "values": [
        3.6763043203899888,
        0.01751427379747339
      ]
    }
  },
  "Results": {
    "l1_norm": {
      "L1": 1.7499718193116334,
      "L2": 0.812246725136353
    },
    "l2_norm": {
      "L1": 1.0259435783133246,
      "L2": 0.25303990306134727
    },
    "non_zero_results": {
      "L1": 3,
      "L2": 4
    },
    "variables": 6,
    "time": {
      "L1": 0.0011043548583984375,
      "L2": 0.0002808570861816406
    },
    "steps": {
      "L1": 5,
      "L2": 4
    }
  }
}