{
  "points": {
    "p1": {
      "ORIGINAL": {
        "x": 0.6156184929834163,
        "y": 0.08539832151226268
      },
      "L1": {
        "x": 0.6156184929834163,
        "y": 1.2056000408557672,
        "l1_norm": 1.1202017193435045,
        "l2_norm": 1.2548518920201437,
        "non_zero_results": 1
      },
      "L2": {
        "x": 0.943133785289566,
        "y": 0.5697707389197235,
        "l1_norm": 0.8118877097136106,
        "l2_norm": 0.3418829054395302,
        "non_zero_results": 2
      }
    },
    "p2": {
      "ORIGINAL": {
        "x": 1.0189514043843646,
        "y": 3.173
      },
      "L1": {
        "x": 0.9686435768432142,
        "y": 3.173,
        "l1_norm": 0.050307827541150374,
        "l2_norm": 0.002530877511910128,
        "non_zero_results": 1
      },
      "L2": {
        "x": 0.5953798421508164,
        "y": 3.2331036367274364,
        "l1_norm": 0.48367519896098454,
        "l2_norm": 0.18302531548083223,
        "non_zero_results": 2
      }
    },
    "p3": {
      "ORIGINAL": {
        "x": 2.99,
        "y": 0.52793350909513
      },
      "L1": {
        "x": 2.9562771349946586,
        "y": 1.5273647315290861
      },
      "L2": {
        "x": 2.9562771349946586,
        "y": 1.5273647315290861
      }
    },
    "p4": {
      "ORIGINAL": {
        "x": 2.031995020634442,
        "y": -2.517
      },
      "L1": {
        "x": 2.031995020634442,
        "y": -2.517,
        "l1_norm": 0.0,
        "l2_norm": 0.0,
        "non_zero_results": 0
      },
      "L2": {
        "x": 2.031995020634442,
        "y": -2.517,
        "l1_norm": 0.0,
        "l2_norm": 0.0,
        "non_zero_results": 0
      }
    },
    "p5": {
      "ORIGINAL": {
        "x": -1.8489975458714059,
        "y": -2.517
      },
      "L1": {
        "x": -1.8489975458714059,
        "y": -2.517,
        "l1_norm": 0.0,
        "l2_norm": 0.0,
        "non_zero_results": 0
      },
      "L2": {
        "x": -1.8489975458714059,
        "y": -2.517,
        "l1_norm": 0.0,
        "l2_norm": 0.0,
        "non_zero_results": 0
      }
    },
    "p6": {
      "ORIGINAL": {
        "x": -3.0,
        "y": 1.8055
      },
      "L1": {
        "x": -3.0,
        "y": 1.8055,
        "l1_norm": 0.0,
        "l2_norm": 0.0,
        "non_zero_results": 0
      },
      "L2": {
        "x": -3.0,
        "y": 1.8055,
        "l1_norm": 0.0,
        "l2_norm": 0.0,
        "non_zero_results": 0
      }
    }
  },
  "lines": {
    "l1": [
      "p1",
      "p2"
    ],
    "l2": [
      "p1",
      "p3"
    ],
    "l3": [
      "p1",
      "p4"
    ],
    "l4": [
      "p1",
      "p5"
    ],
    "l5": [
      "p1",
      "p6"
    ],
    "l6": [
      "p2",
      "p3"
    ],
    "l7": [
      "p3",
      "p4"
    ],
    "l8": [
      "p4",
      "p5"
    ],
    "l9": [
      "p5",
      "p6"
    ],
    "l10": [
      "p6",
      "p2"
    ]
  },
  "circles": {},
  "constraints": {
    "c1": {
      "type": "ANGLE",
      "entities": [
        "l1",
        "l2"
      ],
      "value": -1.2566370614359172
    }
  },
  "moves": {
    "m1": {
      "point": "p3",
      "values": [
        2.9562771349946586,
        1.5273647315290861
      ]
    }
  },
  "Results": {
    "l1_norm": {
      "L1": 1.170509546884655,
      "L2": 1.295562908674595
    },
    "l2_norm": {
      "L1": 1.2573827695320539,
      "L2": 0.5249082209203624
    },
    "non_zero_results": {
      "L1": 2,
      "L2": 4
    },
    "variables": 12,
    "time": {
      "L1": 0.0006821155548095703,
      "L2": 0.0003790855407714844
    },
    "steps": {
      "L1": 4,
      "L2": 4
    }
  }
}