{
  "points": {
    "p1": {
      "ORIGINAL": {
        "x": 0.0,
        "y": 1.0
      },
      "L1": {
        "x": -2.9675002804195953,
        "y": 3.6821525187758315
      },
      "L2": {
        "x": -2.9675004468475623,
        "y": 3.6821524348005443
      }
    },
    "p2": {
      "ORIGINAL": {
        "x": 4.0,
        "y": 1.0
      },
      "L1": {
        "x": 0.050023136691486836,
        "y": 1.0564045439720304,
        "l1_norm": 4.006381407280544,
        "l2_norm": 15.605498693253253,
        "non_zero_results": 2
      },
      "L2": {
        "x": -0.09273199599663041,
        "y": 0.9008386527917136,
        "l1_norm": 4.191893343204917,
        "l2_norm": 16.760288163834726,
        "non_zero_results": 2
      }
    },
    "p3": {
      "ORIGINAL": {
        "x": 4.0,
        "y": 3.0
      },
      "L1": {
        "x": 1.7412749107669294,
        "y": 3.0,
        "l1_norm": 2.258725089233071,
        "l2_norm": 5.101839028730944,
        "non_zero_results": 1
      },
      "L2": {
        "x": 2.2705583419897697,
        "y": 3.3435376922856554,
        "l1_norm": 2.0729793502958858,
        "l2_norm": 3.108986594482128,
        "non_zero_results": 2
      }
    }
  },
  "lines": {
    "l1": [
      "p1",
      "p2"
    ],
    "l2": [
      "p2",
      "p3"
    ],
    "l3": [
      "p3",
      "p1"
    ]
  },
  "circles": {},
  "constraints": {
    "c1": {
      "type": "LENGTH",
      "entities": [
        "l1"
      ],
      "value": 4
    },
    "c4": {
      "type": "ORTHOGONAL",
      "entities": [
        "l1",
        "l2"
      ]
    }
  },
  "moves": {
    "m1": {
      "point": "p1",
      "values": [
        -2.967500272287176,
        3.6821525187758315
      ]
    }
  },
  "Results": {
    "l1_norm": {
      "L1": 6.2651064965136145,
      "L2": 6.264872693500803
    },
    "l2_norm": {
      "L1": 20.707337721984196,
      "L2": 19.869274758316855
    },
    "non_zero_results": {
      "L1": 3,
      "L2": 4
    },
    "variables": 6,
    "time": {
      "L1": 0.0013051033020019531,
      "L2": 0.0002391338348388672
    },
    "steps": {
      "L1": 5,
      "L2": 5
    }
  }
}