{
  "points": {
    "p1": {
      "ORIGINAL": {
        "x": 0.0,
        "y": 1.0
      },
      "L1": {
        "x": 3.962817994615128,
        "y": 1.0452662169290818,
        "l1_norm": 4.00808421154421,
        "l2_norm": 15.705975488840535,
        "non_zero_results": 2
      },
      "L2": {
        "x": 4.108701464119498,
        "y": 0.8749800556753683,
        "l1_norm": 4.23372140844413,
        "l2_norm": 16.897057707736643,
        "non_zero_results": 2
      }
    },
    "p2": {
      "ORIGINAL": {
        "x": 4.0,
        "y": 1.0
      },
      "L1": {
        "x": 7.0722632520994,
        "y": 3.5614836540176515
      },
      "L2": {
        "x": 7.072263245584792,
        "y": 3.5614836509527428
      }
    },
    "p3": {
      "ORIGINAL": {
        "x": 4.0,
        "y": 3.0
      },
      "L1": {
        "x": 7.526625636347474,
        "y": 3.0,
        "l1_norm": 3.5266256363474744,
        "l2_norm": 12.437088378943228,
        "non_zero_results": 1
      },
      "L2": {
        "x": 6.657041530083257,
        "y": 4.019527038297532,
        "l1_norm": 3.676568568380789,
        "l2_norm": 8.099305074406912,
        "non_zero_results": 2
      }
    }
  },
  "lines": {
    "l1": [
      "p1",
      "p2"
    ],
    "l2": [
      "p2",
      "p3"
    ],
    "l3": [
      "p3",
      "p1"
    ]
  },
  "circles": {},
  "constraints": {
    "c1": {
      "type": "LENGTH",
      "entities": [
        "l1"
      ],
      "value": 4
    },
    "c4": {
      "type": "ORTHOGONAL",
      "entities": [
        "l1",
        "l2"
      ]
    }
  },
  "moves": {
    "m1": {
      "point": "p2",
      "values": [
        7.0722632520994,
        3.5614836540176515
      ]
    }
  },
  "Results": {
    "l1_norm": {
      "L1": 7.534709847891684,
      "L2": 7.910289976824919
    },
    "l2_norm": {
      "L1": 28.143063867783763,
      "L2": 24.996362782143557
    },
    "non_zero_results": {
      "L1": 3,
      "L2": 4
    },
    "variables": 6,
    "time": {
      "L1": 0.0006017684936523438,
      "L2": 0.0002372264862060547
    },
    "steps": {
      "L1": 4,
      "L2": 5
    }
  }
}