{
  "points": {
    "p1": {
      "ORIGINAL": {
        "x": 0.039,
        "y": 0.02701158784136345
      },
      "L1": {
        "x": 0.039,
        "y": 0.02701158784136345,
        "l1_norm": 0.0,
        "l2_norm": 0.0,
        "non_zero_results": 0
      },
      "L2": {
        "x": -0.6024425455120616,
        "y": 0.10868467488929028,
        "l1_norm": 0.7231156325599885,
        "l2_norm": 0.4181190323409314,
        "non_zero_results": 2
      }
    },
    "p2": {
      "ORIGINAL": {
        "x": 0.0968479252882644,
        "y": 3.263
      },
      "L1": {
        "x": 0.0968479252882644,
        "y": 3.263,
        "l1_norm": 0.0,
        "l2_norm": 0.0,
        "non_zero_results": 0
      },
      "L2": {
        "x": 0.09671947771557395,
        "y": 3.265273178116942,
        "l1_norm": 0.0024016256896327304,
        "l2_norm": 5.183837530275302e-06,
        "non_zero_results": 2
      }
    },
    "p3": {
      "ORIGINAL": {
        "x": 3.1337363070211173,
        "y": 0.972
      },
      "L1": {
        "x": 3.1337363070211173,
        "y": 0.972,
        "l1_norm": 0.0,
        "l2_norm": 0.0,
        "non_zero_results": 0
      },
      "L2": {
        "x": 3.342765145475615,
        "y": 1.0274910845702394,
        "l1_norm": 0.26451992302473726,
        "l2_norm": 0.04677231577241801,
        "non_zero_results": 2
      }
    },
    "p4": {
      "ORIGINAL": {
        "x": 1.893,
        "y": -2.6230575905296067
      },
      "L1": {
        "x": 1.893,
        "y": -2.6230575905296063,
        "l1_norm": 4.440892098500626e-16,
        "l2_norm": 1.9721522630525295e-31,
        "non_zero_results": 1
      },
      "L2": {
        "x": 2.070607457516646,
        "y": -2.766965702473331,
        "l1_norm": 0.3215155694603704,
        "l2_norm": 0.052253953648734745,
        "non_zero_results": 2
      }
    },
    "p5": {
      "ORIGINAL": {
        "x": -1.909,
        "y": -2.5532955256185668
      },
      "L1": {
        "x": -3.9063209315246765,
        "y": -2.449810761071325,
        "l1_norm": 2.1008056960719186,
        "l2_norm": 3.9999999999999996,
        "non_zero_results": 2
      },
      "L2": {
        "x": -3.2648783860126156,
        "y": -2.531483848119252,
        "l1_norm": 1.3776900635119305,
        "l2_norm": 1.8388819469315096,
        "non_zero_results": 2
      }
    },
    "p6": {
      "ORIGINAL": {
        "x": -3.019,
        "y": 1.0824264121634164
      },
      "L1": {
        "x": -3.0190000000000006,
        "y": 1.0824264121634164,
        "l1_norm": 4.440892098500626e-16,
        "l2_norm": 1.9721522630525295e-31,
        "non_zero_results": 1
      },
      "L2": {
        "x": -2.8198950143645924,
        "y": 1.019157030383745,
        "l1_norm": 0.26237436741507913,
        "l2_norm": 0.043645809975657715,
        "non_zero_results": 2
      }
    },
    "p7": {
      "ORIGINAL": {
        "x": 0.06792396264413221,
        "y": 1.6450057939206817
      },
      "L1": {
        "x": 0.0679239626441322,
        "y": 1.6450057939206817,
        "l1_norm": 1.3877787807814457e-17,
        "l2_norm": 1.925929944387236e-34,
        "non_zero_results": 1
      },
      "L2": {
        "x": -0.2528615338982438,
        "y": 1.686978926503116,
        "l1_norm": 0.3627586291248104,
        "l2_norm": 0.10466507865072132,
        "non_zero_results": 2
      }
    },
    "p8": {
      "ORIGINAL": {
        "x": 1.2430000808939146,
        "y": 1.6239996261479137
      },
      "L1": {
        "x": 1.2430000808939146,
        "y": 1.6239996261479137,
        "l1_norm": 0.0,
        "l2_norm": 0.0,
        "non_zero_results": 0
      },
      "L2": {
        "x": 1.1836833398584852,
        "y": 1.3687943993257365,
        "l1_norm": 0.31452196785760655,
        "l2_norm": 0.0686481835644231,
        "non_zero_results": 2
      }
    },
    "p9": {
      "ORIGINAL": {
        "x": 1.5863681535105587,
        "y": 0.49950579392068173
      },
      "L1": {
        "x": 1.5863681535105587,
        "y": 0.49950579392068173,
        "l1_norm": 0.0,
        "l2_norm": 0.0,
        "non_zero_results": 0
      },
      "L2": {
        "x": 1.370161299981777,
        "y": 0.5680878797297648,
        "l1_norm": 0.28478893933786487,
        "l2_norm": 0.05144890600674053,
        "non_zero_results": 2
      }
    },
    "p10": {
      "ORIGINAL": {
        "x": 1.9294345225255194,
        "y": -0.6239999911748865
      },
      "L1": {
        "x": 1.9294345225255194,
        "y": -0.6239999911748862,
        "l1_norm": 2.220446049250313e-16,
        "l2_norm": 4.930380657631324e-32,
        "non_zero_results": 1
      },
      "L2": {
        "x": 1.620183726016437,
        "y": -0.50546840777356,
        "l1_norm": 0.427782379910409,
        "l2_norm": 0.10968579140512758,
        "non_zero_results": 2
      }
    },
    "p11": {
      "ORIGINAL": {
        "x": 0.966,
        "y": -1.2980230013441214
      },
      "L1": {
        "x": 0.966,
        "y": -1.2980230013441214,
        "l1_norm": 0.0,
        "l2_norm": 0.0,
        "non_zero_results": 0
      },
      "L2": {
        "x": 0.7340824560022923,
        "y": -1.3291405137920205,
        "l1_norm": 0.26303505644560676,
        "l2_norm": 0.05475404679487384,
        "non_zero_results": 2
      }
    },
    "p12": {
      "ORIGINAL": {
        "x": 0.0033148641860392615,
        "y": -1.9715217372889065
      },
      "L1": {
        "x": -1.0109830264188617,
        "y": -2.681128982461826,
        "l1_norm": 1.7239051357778203,
        "l2_norm": 1.5323426532874513,
        "non_zero_results": 2
      },
      "L2": {
        "x": -0.593331390176214,
        "y": -2.563033066753221,
        "l1_norm": 1.1881575838265679,
        "l2_norm": 0.7058724057291474,
        "non_zero_results": 2
      }
    },
    "p13": {
      "ORIGINAL": {
        "x": -0.935,
        "y": -1.2631419688886016
      },
      "L1": {
        "x": -1.9336604657623384,
        "y": -1.2113995866149807
      },
      "L2": {
        "x": -1.9336604657623384,
        "y": -1.2113995866149807
      }
    },
    "p14": {
      "ORIGINAL": {
        "x": -1.872999944258877,
        "y": -0.5549999489388252
      },
      "L1": {
        "x": -2.0406991312736276,
        "y": -1.040898102037556,
        "l1_norm": 0.6535973401134815,
        "l2_norm": 0.264220032510166,
        "non_zero_results": 2
      },
      "L2": {
        "x": -2.2918101292464788,
        "y": -0.8502292703971391,
        "l1_norm": 0.7140395064459157,
        "l2_norm": 0.2625623232980857,
        "non_zero_results": 2
      }
    },
    "p15": {
      "ORIGINAL": {
        "x": -1.49,
        "y": 0.5547190000023899
      },
      "L1": {
        "x": -1.4900000000000002,
        "y": 0.5547190000023899,
        "l1_norm": 2.220446049250313e-16,
        "l2_norm": 4.930380657631324e-32,
        "non_zero_results": 1
      },
      "L2": {
        "x": -1.7111687799383268,
        "y": 0.5639208526365176,
        "l1_norm": 0.2303706325724545,
        "l2_norm": 0.04900030331130825,
        "non_zero_results": 2
      }
    },
    "p16": {
      "ORIGINAL": {
        "x": -1.1064610767450938,
        "y": 1.6659996076695156
      },
      "L1": {
        "x": -1.1064610767450938,
        "y": 1.6659996076695156,
        "l1_norm": 0.0,
        "l2_norm": 0.0,
        "non_zero_results": 0
      },
      "L2": {
        "x": -1.1669202184657423,
        "y": 1.8894364589301464,
        "l1_norm": 0.28389599298127943,
        "l2_norm": 0.05357933431886274,
        "non_zero_results": 2
      }
    }
  },
  "lines": {
    "l1": [
      "p1",
      "p2"
    ],
    "l2": [
      "p1",
      "p3"
    ],
    "l3": [
      "p1",
      "p4"
    ],
    "l4": [
      "p1",
      "p5"
    ],
    "l5": [
      "p1",
      "p6"
    ],
    "l6": [
      "p2",
      "p3"
    ],
    "l7": [
      "p3",
      "p4"
    ],
    "l8": [
      "p4",
      "p5"
    ],
    "l9": [
      "p5",
      "p6"
    ],
    "l10": [
      "p6",
      "p2"
    ],
    "l11": [
      "p7",
      "p8"
    ],
    "l12": [
      "p8",
      "p9"
    ],
    "l13": [
      "p9",
      "p10"
    ],
    "l14": [
      "p10",
      "p11"
    ],
    "l15": [
      "p11",
      "p12"
    ],
    "l16": [
      "p12",
      "p13"
    ],
    "l17": [
      "p13",
      "p14"
    ],
    "l18": [
      "p14",
      "p15"
    ],
    "l19": [
      "p15",
      "p16"
    ],
    "l20": [
      "p16",
      "p7"
    ]
  },
  "circles": {},
  "constraints": {
    "c6": {
      "type": "MIDPOINT",
      "entities": [
        "p1",
        "p2",
        "p7"
      ]
    },
    "c7": {
      "type": "MIDPOINT",
      "entities": [
        "p1",
        "p3",
        "p9"
      ]
    },
    "c8": {
      "type": "ORTHOGONAL",
      "entities": [
        "l1",
        "l11"
      ]
    },
    "c9": {
      "type": "ORTHOGONAL",
      "entities": [
        "l2",
        "l12"
      ]
    },
    "c10": {
      "type": "MIDPOINT",
      "entities": [
        "p1",
        "p4",
        "p11"
      ]
    },
    "c11": {
      "type": "ORTHOGONAL",
      "entities": [
        "l2",
        "l13"
      ]
    },
    "c12": {
      "type": "ORTHOGONAL",
      "entities": [
        "l3",
        "l14"
      ]
    },
    "c13": {
      "type": "MIDPOINT",
      "entities": [
        "p1",
        "p5",
        "p13"
      ]
    },
    "c14": {
      "type": "ORTHOGONAL",
      "entities": [
        "l3",
        "l15"
      ]
    },
    "c15": {
      "type": "ORTHOGONAL",
      "entities": [
        "l4",
        "l16"
      ]
    },
    "c16": {
      "type": "MIDPOINT",
      "entities": [
        "p1",
        "p6",
        "p15"
      ]
    },
    "c17": {
      "type": "ORTHOGONAL",
      "entities": [
        "l4",
        "l17"
      ]
    },
    "c18": {
      "type": "ORTHOGONAL",
      "entities": [
        "l5",
        "l18"
      ]
    },
    "c19": {
      "type": "ORTHOGONAL",
      "entities": [
        "l5",
        "l19"
      ]
    },
    "c20": {
      "type": "ORTHOGONAL",
      "entities": [
        "l1",
        "l20"
      ]
    }
  },
  "moves": {
    "m1": {
      "point": "p13",
      "values": [
        -1.9336604657623384,
        -1.2113995866149807
      ]
    }
  },
  "Results": {
    "l1_norm": {
      "L1": 4.478308171963222,
      "L2": 7.020967870164255
    },
    "l2_norm": {
      "L1": 5.796562685797617,
      "L2": 3.8598946155860725
    },
    "non_zero_results": {
      "L1": 11,
      "L2": 30
    },
    "variables": 32,
    "time": {
      "L1": 0.002528667449951172,
      "L2": 0.008201360702514648
    },
    "steps": {
      "L1": 2,
      "L2": 4
    }
  }
}