{
  "points": {
    "p1": {
      "ORIGINAL": {
        "x": 0.6156184929834163,
        "y": 0.08539832151226268
      },
      "L1": {
        "x": 0.09949303332568273,
        "y": -0.2893253537537089,
        "l1_norm": 0.8908491349237051,
        "l2_norm": 0.40680332291174415,
        "non_zero_results": 2
      },
      "L2": {
        "x": 0.06679830917587948,
        "y": -0.2159482735204619,
        "l1_norm": 0.8501667788402614,
        "l2_norm": 0.3920133644923554,
        "non_zero_results": 2
      }
    },
    "p2": {
      "ORIGINAL": {
        "x": 1.0189514043843646,
        "y": 3.173
      },
      "L1": {
        "x": 1.0175597495859734,
        "y": 3.173,
        "l1_norm": 0.0013916547983912064,
        "l2_norm": 1.9367030778852694e-06,
        "non_zero_results": 1
      },
      "L2": {
        "x": 0.9619484525421074,
        "y": 3.178878069837915,
        "l1_norm": 0.06288102168017229,
        "l2_norm": 0.003283888223750104,
        "non_zero_results": 2
      }
    },
    "p3": {
      "ORIGINAL": {
        "x": 2.99,
        "y": 0.52793350909513
      },
      "L1": {
        "x": 2.99,
        "y": -0.1302885142000761,
        "l1_norm": 0.6582220232952061,
        "l2_norm": 0.4332562319508348,
        "non_zero_results": 1
      },
      "L2": {
        "x": 3.09394979427641,
        "y": -0.045197589747329965,
        "l1_norm": 0.6770808931188697,
        "l2_norm": 0.33928481619047357,
        "non_zero_results": 2
      }
    },
    "p4": {
      "ORIGINAL": {
        "x": 2.031995020634442,
        "y": -2.517
      },
      "L1": {
        "x": 1.119792977956727,
        "y": -2.926740690357456
      },
      "L2": {
        "x": 1.119792977956727,
        "y": -2.926740690357456
      }
    },
    "p5": {
      "ORIGINAL": {
        "x": -1.8489975458714059,
        "y": -2.517
      },
      "L1": {
        "x": -2.63684958658715,
        "y": -2.5169998192810477,
        "l1_norm": 0.7878522214346966,
        "l2_norm": 0.6207108380599955,
        "non_zero_results": 2
      },
      "L2": {
        "x": -2.2687097075775924,
        "y": -2.1226724291339494,
        "l1_norm": 0.814039732572237,
        "l2_norm": 0.3316525318292002,
        "non_zero_results": 2
      }
    },
    "p6": {
      "ORIGINAL": {
        "x": -3.0,
        "y": 1.8055
      },
      "L1": {
        "x": -3.0,
        "y": 1.7120485760147262,
        "l1_norm": 0.09345142398527395,
        "l2_norm": 0.008733168644875436,
        "non_zero_results": 1
      },
      "L2": {
        "x": -3.0185796655075023,
        "y": 1.7702762703606556,
        "l1_norm": 0.053803395146846844,
        "l2_norm": 0.0015859151000763086,
        "non_zero_results": 2
      }
    }
  },
  "lines": {
    "l1": [
      "p1",
      "p2"
    ],
    "l2": [
      "p1",
      "p3"
    ],
    "l3": [
      "p1",
      "p4"
    ],
    "l4": [
      "p1",
      "p5"
    ],
    "l5": [
      "p1",
      "p6"
    ],
    "l6": [
      "p2",
      "p3"
    ],
    "l7": [
      "p3",
      "p4"
    ],
    "l8": [
      "p4",
      "p5"
    ],
    "l9": [
      "p5",
      "p6"
    ],
    "l10": [
      "p6",
      "p2"
    ]
  },
  "circles": {},
  "constraints": {
    "c1": {
      "type": "ANGLE",
      "entities": [
        "l1",
        "l2"
      ],
      "value": -1.2566370614359172
    },
    "c2": {
      "type": "ANGLE",
      "entities": [
        "l2",
        "l3"
      ],
      "value": -1.2566370614359172
    },
    "c3": {
      "type": "ANGLE",
      "entities": [
        "l3",
        "l4"
      ],
      "value": -1.2566370614359172
    },
    "c4": {
      "type": "ANGLE",
      "entities": [
        "l4",
        "l5"
      ],
      "value": -1.2566370614359172
    },
    "c5": {
      "type": "ANGLE",
      "entities": [
        "l5",
        "l1"
      ],
      "value": -1.2566370614359172
    }
  },
  "moves": {
    "m1": {
      "point": "p4",
      "values": [
        1.119792977956727,
        -2.926740690357456
      ]
    }
  },
  "Results": {
    "l1_norm": {
      "L1": 2.431766458437273,
      "L2": 2.457971821358387
    },
    "l2_norm": {
      "L1": 1.4695054982705278,
      "L2": 1.0678205158358556
    },
    "non_zero_results": {
      "L1": 7,
      "L2": 10
    },
    "variables": 12,
    "time": {
      "L1": 0.0038564205169677734,
      "L2": 0.0016355514526367188
    },
    "steps": {
      "L1": 4,
      "L2": 4
    }
  }
}