{
  "points": {
    "p1": {
      "ORIGINAL": {
        "x": 0.0,
        "y": 1.0
      },
      "L1": {
        "x": -1.924281713864131,
        "y": 5.615884799945107
      },
      "L2": {
        "x": -1.9218768994007225,
        "y": 5.6158843067650945
      }
    },
    "p2": {
      "ORIGINAL": {
        "x": 4.0,
        "y": 1.0
      },
      "L1": {
        "x": -0.21132390475642165,
        "y": 2.001223606385834,
        "l1_norm": 5.212547511142256,
        "l2_norm": 18.73769774075713,
        "non_zero_results": 2
      },
      "L2": {
        "x": 0.20301040902749048,
        "y": 2.2269532176922247,
        "l1_norm": 5.023942808664734,
        "l2_norm": 15.922544152358888,
        "non_zero_results": 2
      }
    },
    "p3": {
      "ORIGINAL": {
        "x": 4.0,
        "y": 3.0
      },
      "L1": {
        "x": 4.386066359839965,
        "y": 4.1798885305835105,
        "l1_norm": 1.565954890423476,
        "l2_norm": 1.5411841788025973,
        "non_zero_results": 2
      },
      "L2": {
        "x": 3.2533766184740083,
        "y": 4.13955759770297,
        "l1_norm": 1.8861809792289614,
        "l2_norm": 1.85603799232387,
        "non_zero_results": 2
      }
    }
  },
  "lines": {
    "l1": [
      "p1",
      "p2"
    ],
    "l2": [
      "p2",
      "p3"
    ],
    "l3": [
      "p3",
      "p1"
    ]
  },
  "circles": {},
  "constraints": {
    "c1": {
      "type": "LENGTH",
      "entities": [
        "l1"
      ],
      "value": 4
    },
    "c4": {
      "type": "ORTHOGONAL",
      "entities": [
        "l1",
        "l2"
      ]
    }
  },
  "moves": {
    "m1": {
      "point": "p1",
      "values": [
        -1.9218760401325883,
        5.615884799945107
      ]
    }
  },
  "Results": {
    "l1_norm": {
      "L1": 6.778502401565732,
      "L2": 6.910123787893696
    },
    "l2_norm": {
      "L1": 20.27888191955973,
      "L2": 17.77858214468276
    },
    "non_zero_results": {
      "L1": 4,
      "L2": 4
    },
    "variables": 6,
    "time": {
      "L1": 0.0009603500366210938,
      "L2": 0.000247955322265625
    },
    "steps": {
      "L1": 6,
      "L2": 5
    }
  }
}