{
  "points": {
    "p1": {
      "ORIGINAL": {
        "x": 0.0,
        "y": 1.0
      },
      "L1": {
        "x": -0.5753943429285724,
        "y": 1.0,
        "l1_norm": 0.5753943429285724,
        "l2_norm": 0.33107864987420355,
        "non_zero_results": 1
      },
      "L2": {
        "x": -0.48155514412306716,
        "y": 0.4989140868728271,
        "l1_norm": 0.98264105725024,
        "l2_norm": 0.4829824491658806,
        "non_zero_results": 2
      }
    },
    "p2": {
      "ORIGINAL": {
        "x": 4.0,
        "y": 1.0
      },
      "L1": {
        "x": 3.0496783295798546,
        "y": 2.6908128574838255,
        "l1_norm": 2.641134527903971,
        "l2_norm": 3.761959396302754,
        "non_zero_results": 2
      },
      "L2": {
        "x": 3.4033245868578303,
        "y": 1.4516519709837223,
        "l1_norm": 1.048327384125892,
        "l2_norm": 0.5600110515418599,
        "non_zero_results": 2
      }
    },
    "p3": {
      "ORIGINAL": {
        "x": 4.0,
        "y": 3.0
      },
      "L1": {
        "x": 3.1545935712580873,
        "y": 2.465876446651296
      },
      "L2": {
        "x": 3.1545935712580873,
        "y": 2.465876446651296
      }
    }
  },
  "lines": {
    "l1": [
      "p1",
      "p2"
    ],
    "l2": [
      "p2",
      "p3"
    ],
    "l3": [
      "p3",
      "p1"
    ]
  },
  "circles": {},
  "constraints": {
    "c1": {
      "type": "LENGTH",
      "entities": [
        "l1"
      ],
      "value": 4
    },
    "c4": {
      "type": "ORTHOGONAL",
      "entities": [
        "l1",
        "l2"
      ]
    }
  },
  "moves": {
    "m1": {
      "point": "p3",
      "values": [
        3.1545935712580873,
        2.465876446651296
      ]
    }
  },
  "Results": {
    "l1_norm": {
      "L1": 3.2165288708325432,
      "L2": 2.0309684413761318
    },
    "l2_norm": {
      "L1": 4.093038046176957,
      "L2": 1.0429935007077407
    },
    "non_zero_results": {
      "L1": 3,
      "L2": 4
    },
    "variables": 6,
    "time": {
      "L1": 0.0007474422454833984,
      "L2": 0.00021195411682128906
    },
    "steps": {
      "L1": 4,
      "L2": 4
    }
  }
}