{
  "points": {
    "p1": {
      "ORIGINAL": {
        "x": 0.0,
        "y": 1.0
      },
      "L1": {
        "x": -0.0330569639937207,
        "y": 1.0,
        "l1_norm": 0.0330569639937207,
        "l2_norm": 0.0010927628684821466,
        "non_zero_results": 1
      },
      "L2": {
        "x": -0.04419049057053545,
        "y": 0.9008510189414151,
        "l1_norm": 0.1433394716291204,
        "l2_norm": 0.011783319901820218,
        "non_zero_results": 2
      }
    },
    "p2": {
      "ORIGINAL": {
        "x": 4.0,
        "y": 1.0
      },
      "L1": {
        "x": 3.9360846524830975,
        "y": 0.5041019980360937
      },
      "L2": {
        "x": 3.9360846524831037,
        "y": 0.5041019980360937
      }
    },
    "p3": {
      "ORIGINAL": {
        "x": 4.0,
        "y": 3.0
      },
      "L1": {
        "x": 4.247918029035243,
        "y": 3.0,
        "l1_norm": 0.24791802903524296,
        "l2_norm": 0.061463349120719574,
        "non_zero_results": 1
      },
      "L2": {
        "x": 4.184480808537825,
        "y": 2.996067934886166,
        "l1_norm": 0.18841287365165904,
        "l2_norm": 0.03404862985482904,
        "non_zero_results": 2
      }
    }
  },
  "lines": {
    "l1": [
      "p1",
      "p2"
    ],
    "l2": [
      "p2",
      "p3"
    ],
    "l3": [
      "p3",
      "p1"
    ]
  },
  "circles": {},
  "constraints": {
    "c1": {
      "type": "LENGTH",
      "entities": [
        "l1"
      ],
      "value": 4
    },
    "c4": {
      "type": "ORTHOGONAL",
      "entities": [
        "l1",
        "l2"
      ]
    }
  },
  "moves": {
    "m1": {
      "point": "p2",
      "values": [
        3.9360846524831037,
        0.5041019980360937
      ]
    }
  },
  "Results": {
    "l1_norm": {
      "L1": 0.28097499302896367,
      "L2": 0.33175234528077946
    },
    "l2_norm": {
      "L1": 0.06255611198920172,
      "L2": 0.045831949756649254
    },
    "non_zero_results": {
      "L1": 2,
      "L2": 4
    },
    "variables": 6,
    "time": {
      "L1": 0.0010356903076171875,
      "L2": 0.0002651214599609375
    },
    "steps": {
      "L1": 5,
      "L2": 4
    }
  }
}